pytconf/__init__.py
pytconf/color_utils.py
pytconf/config.py
pytconf/convert.py
pytconf/data.py
pytconf/enum_subset.py
pytconf/errors_collector.py
pytconf/extended_enum.py
pytconf/param.py
pytconf/param_collector.py
pytconf/pydoc.py
pytconf/registry.py
pytconf/static.py
pytconf/utils.py
pytconf-0.1.19.dist-info/licenses/LICENSE
pytconf-0.1.19.dist-info/METADATA
pytconf-0.1.19.dist-info/WHEEL
pytconf-0.1.19.dist-info/top_level.txt
pytconf-0.1.19.dist-info/RECORD
